{
  "fixDate": "2026-06-09T10:45:20.398Z",
  "totalApplied": 6,
  "totalNeedReview": 0,
  "fixes": [
    {
      "audioId": "official_intro_scene_1-4",
      "path": "public/audio/ui/official_intro_scene_1-4.mp3",
      "oldTts": "مَرْحَبًا بِكُمْ فِي هَذَا التَّطْبِيقِ التَّعْلِيمِي الْمُهْدَى مِنْ جَامِعَةِ الْأَزْهَر الشَّرِيف كُلِّيَّة التَّرْبِيَة بَنِينَ بِالْقَاهِرَة قِسْم الْمَنَاهِج وَطُرُق التَّدْرِيس",
      "newTts": "مَرْحَبًا بِكُمْ فِي هَذَا التَّطْبِيقِ التَّعْلِيمِي.\nهُوَ مُهْدَى مِنْ جَامِعَةِ الْأَزْهَرِ الشَّرِيفِ.\nكُلِّيَّةُ التَّرْبِيَةِ بَنِينَ بِالْقَاهِرَةِ، قِسْمُ الْمَنَاهِجِ وَطُرُقِ التَّدْرِيسِ.",
      "notes": "Split into 3 natural sentences for better breathing pauses"
    },
    {
      "audioId": "official_intro_scene_2",
      "path": "public/audio/ui/official_intro_scene_2.mp3",
      "oldTts": "هَذَا الْعَمَل مُقَدَّم اسْتِكْمَالًا لِمُتَطَلَّبَاتِ الْحُصُول عَلَى دَرَجَةِ الْمَاجِسْتِر فِي التَّرْبِيَهْ تَخَصُّص مَنَاهِج وَطُرُق تَدْرِيس اللُّغَهْ الْعَرَبِيَّهْ مِنْ إِعْدَاد الْبَاحِث مُصْطَفَى أَحْمَد مُحَمَّد حَسَن حَسَّان مُعَلِّم اللُّغَهْ الْعَرَبِيَّهْ بِوِزَارَةِ التَّرْبِيَهْ وَالتَّعْلِيم",
      "newTts": "هَذَا الْعَمَلُ مُقَدَّمٌ اسْتِكْمَالًا لِمُتَطَلَّبَاتِ الْحُصُولِ عَلَى دَرَجَةِ الْمَاجِسْتِيرِ.\nفِي التَّرْبِيَةِ، تَخَصُّصُ مَنَاهِجِ وَطُرُقِ تَدْرِيسِ اللُّغَةِ الْعَرَبِيَّةِ.\nمِنْ إِعْدَادِ الْبَاحِثِ مُصْطَفَى أَحْمَدَ مُحَمَّدِ حَسَنِ حَسَّانَ.\nمُعَلِّمِ اللُّغَةِ الْعَرَبِيَّةِ بِوِزَارَةِ التَّرْبِيَةِ وَالتَّعْلِيمِ.",
      "notes": "Split 31-word run-on into 4 natural sentences with proper academic introduction pacing"
    },
    {
      "audioId": "official_intro_scene_3",
      "path": "public/audio/ui/official_intro_scene_3.mp3",
      "oldTts": "وَيَأْتِي هَذَا الْعَمَل تَحْت إِشْرَاف نُخْبَةٍ مِنَ الْعُلَمَاءِ الْأَجْلَاءِ الْأَسْتَاذ الدُّكْتُور خَالِد فَارُوق الْهَوَارِي الدُّكْتُور بَاسِم مُحَمَّد عُبْدَه الْجُنْدِي وَالدُّكْتُور أَشْرَف مُحَمَّد سَعْد أَسَاتِذَهْ الْمَنَاهِج وَطُرُق التَّدْرِيس بِكُلِّيَّهْ التَّرْبِيَهْ بِجَامِعَهْ الْأَزْهَر",
      "newTts": "وَيَأْتِي هَذَا الْعَمَلُ تَحْتَ إِشْرَافِ نُخْبَةٍ مِنَ الْعُلَمَاءِ الْأَجِلَّاءِ.\nالْأُسْتَاذُ الدُّكْتُورُ خَالِدُ فَارُوقَ الْهَوَارِيِّ.\nالدُّكْتُورُ بَاسِمُ مُحَمَّدِ عُبْدَةَ الْجُنْدِيِّ.\nوَالدُّكْتُورُ أَشْرَفُ مُحَمَّدِ سَعْدٍ.\nأَسَاتِذَةِ الْمَنَاهِجِ وَطُرُقِ التَّدْرِيسِ بِكُلِّيَّةِ التَّرْبِيَةِ بِجَامِعَةِ الْأَزْهَرِ.",
      "notes": "Split supervisor listing into separate sentences for clear academic credential presentation"
    },
    {
      "audioId": "welcome_intro_scene_1",
      "path": "public/audio/ui/welcome_intro_scene_1.mp3",
      "oldTts": "عَزِيزِي تِلْمِيذ الصَّفّ الْأَوَّل الِابْتِدَائِي أَهْلًا وَمَرْحَبًا بِكَ يَا بَطَل فِي رِحْلَة مُمْتِعَة وَشَيِّقَة مَلِيئَة بِالْأَلْعَاب اللُّغَوِيَّة الْإِلِكْتُرُونِيَّة الْمُرْتَبِطَة بِالْأَصْوَات وَالْحُرُوف الْجَمِيلَة",
      "newTts": "عَزِيزِي تِلْمِيذِ الصَّفِّ الْأَوَّلِ الِابْتِدَائِيِّ، أَهْلًا وَسَهْلًا بِكَ يَا بَطَلُ.\nفِي رِحْلَةٍ مُمْتِعَةٍ وَشَيِّقَةٍ، مَلِيئَةٍ بِالْأَلْعَابِ اللُّغَوِيَّةِ الْإِلِكْتُرُونِيَّةِ.\nالْمُرْتَبِطَةِ بِالْأَصْوَاتِ وَالْحُرُوفِ الْجَمِيلَةِ.",
      "notes": "Split welcome message into 3 sentences with natural greeting flow and pauses"
    },
    {
      "audioId": "welcome_intro_scene_2",
      "path": "public/audio/ui/welcome_intro_scene_2.mp3",
      "oldTts": "عَزِيزِي التِّلْمِيذ فِي هَذَا التَّطْبِيق سَوْف تَتَعَلَّم كَيْف تَسْمَع الْأَصْوَات وَتَتَعَرَّف عَلَى الْحُرُوف وَالْكَلِمَات وَتُحَلِّلُهَا وَتَدْمُجُهَا بِطَرِيقَة سَهْلَة وَمَرْحَة",
      "newTts": "عَزِيزِي التِّلْمِيذُ، فِي هَذَا التَّطْبِيقِ سَوْفَ تَتَعَلَّمُ.\nكَيْفَ تَسْمَعُ الْأَصْوَاتَ، وَتَتَعَرَّفُ عَلَى الْحُرُوفِ وَالْكَلِمَاتِ.\nوَتُحَلِّلُهَا، وَتَدْمُجُهَا بِطَرِيقَةٍ سَهْلَةٍ وَمَرِحَةٍ.",
      "notes": "Split learning objectives into 3 sentences with pauses between skills"
    },
    {
      "audioId": "welcome_intro_scene_3",
      "path": "public/audio/ui/welcome_intro_scene_3.mp3",
      "oldTts": "هَيَا بِنَا عَزِيزِي التِّلْمِيذ نَنْطَلِق نَلْعَب وَنَتَعَلَّم الْأَصْوَات وَالْحُرُوف فِي مُغَامَرَات مُمْتِعَهْ تُسَاعِدُك عَلَى التَّمْيِيز بَيْن الْأَصْوَات وَالتَّعَرُّف عَلَى الْحُرُوف وَبِنَاء مَهَارَاتِك خَطْوَهْ بِخَطْوَهْ",
      "newTts": "هَيَّا بِنَا يَا عَزِيزِي التِّلْمِيذُ، نَنْطَلِقُ نَلْعَبُ وَنَتَعَلَّمُ.\nالْأَصْوَاتَ وَالْحُرُوفَ، فِي مُغَامَرَاتٍ مُمْتِعَةٍ.\nتُسَاعِدُكَ عَلَى التَّمْيِيزِ بَيْنَ الْأَصْوَاتِ، وَالتَّعَرُّفِ عَلَى الْحُرُوفِ.\nوَبِنَاءِ مَهَارَاتِكَ خَطْوَةً بِخَطْوَةٍ.",
      "notes": "Split call-to-action into 4 energetic sentences with natural game-like pacing"
    }
  ],
  "humanReview": []
}